{
  "apiVersion": "1.0",
  "swaggerVersion": "1.2",
  "basePath": "https://api.usa.dev/",
  "resourcePath": "pages",
  "apis": [
    {
      "path": "api/v1/usagov/pages/usa_gov.json",
      "operations": [
        {
          "summary": "Fetches all pages belonging to USA.gov. Also available in .rss format",
          "parameters": [
            {
              "paramType": "query",
              "name": "page_size",
              "type": "integer",
              "description": "Number of results per page",
              "required": false
            },
            {
              "paramType": "query",
              "name": "page",
              "type": "integer",
              "description": "Page number",
              "required": false
            }
          ],
          "responseMessages": [
            {
              "code": 200,
              "responseModel": null,
              "message": "Success"
            },
            {
              "code": 404,
              "responseModel": null,
              "message": "Not Found"
            },
            {
              "code": 406,
              "responseModel": null,
              "message": "The request you made is not acceptable"
            },
            {
              "code": 500,
              "responseModel": null,
              "message": "Requested Range Not Satisfiable"
            }
          ],
          "method": "get",
          "nickname": "Api::V1::Pages#usa_gov"
        }
      ]
    },
    {
      "path": "api/v1/usagov/pages/gobierno_usa_gov.json",
      "operations": [
        {
          "summary": "Fetches all pages belonging to gobiernoUSA.gov. Also available in .rss format",
          "parameters": [
            {
              "paramType": "query",
              "name": "page_size",
              "type": "integer",
              "description": "Number of results per page",
              "required": false
            },
            {
              "paramType": "query",
              "name": "page",
              "type": "integer",
              "description": "Page number",
              "required": false
            }
          ],
          "responseMessages": [
            {
              "code": 200,
              "responseModel": null,
              "message": "Success"
            },
            {
              "code": 404,
              "responseModel": null,
              "message": "Not Found"
            },
            {
              "code": 406,
              "responseModel": null,
              "message": "The request you made is not acceptable"
            },
            {
              "code": 500,
              "responseModel": null,
              "message": "Requested Range Not Satisfiable"
            }
          ],
          "method": "get",
          "nickname": "Api::V1::Pages#gobierno_usa_gov"
        }
      ]
    },
    {
      "path": "api/v1/usagov/pages/kids_usa_gov.json",
      "operations": [
        {
          "summary": "Fetches all pages belonging to gobiernoUSA.gov. Also available in .rss format",
          "parameters": [
            {
              "paramType": "query",
              "name": "page_size",
              "type": "integer",
              "description": "Number of results per page",
              "required": false
            },
            {
              "paramType": "query",
              "name": "page",
              "type": "integer",
              "description": "Page number",
              "required": false
            }
          ],
          "responseMessages": [
            {
              "code": 200,
              "responseModel": null,
              "message": "Success"
            },
            {
              "code": 404,
              "responseModel": null,
              "message": "Not Found"
            },
            {
              "code": 406,
              "responseModel": null,
              "message": "The request you made is not acceptable"
            },
            {
              "code": 500,
              "responseModel": null,
              "message": "Requested Range Not Satisfiable"
            }
          ],
          "method": "get",
          "nickname": "Api::V1::Pages#kids_usa_gov"
        }
      ]
    },
    {
      "path": "api/v1/usagov/pages.json",
      "operations": [
        {
          "summary": "Fetches all pages in the system across USA.gov web properties. Also available in .rss format",
          "parameters": [
            {
              "paramType": "query",
              "name": "page_size",
              "type": "integer",
              "description": "Number of results per page",
              "required": false
            },
            {
              "paramType": "query",
              "name": "page",
              "type": "integer",
              "description": "Page number",
              "required": false
            }
          ],
          "responseMessages": [
            {
              "code": 200,
              "responseModel": null,
              "message": "Success"
            },
            {
              "code": 404,
              "responseModel": null,
              "message": "Not Found"
            },
            {
              "code": 406,
              "responseModel": null,
              "message": "The request you made is not acceptable"
            },
            {
              "code": 500,
              "responseModel": null,
              "message": "Requested Range Not Satisfiable"
            }
          ],
          "method": "get",
          "nickname": "Api::V1::Pages#index"
        }
      ]
    }
  ]
}